main.py
actiontest112-4.dist-info/METADATA
actiontest112-4.dist-info/WHEEL
actiontest112-4.dist-info/top_level.txt
actiontest112-4.dist-info/RECORD
