Metadata-Version: 2.1
Name: actiontest112
Version: 4
Summary: Fast &  Friendly, Web Framework For Building Async APIs
Home-page: https://github.com/alirn76/panther
Author: Ali RajabNezhad
Author-email: alirn76@yahoo.com
License: MIT
Classifier: Operating System :: OS Independent
Classifier: License :: OSI Approved :: MIT License
Classifier: Programming Language :: Python :: 3.11
Requires-Python: >=3.11
